ddv/__init__.py
ddv/printing.py
ddv_printing-0.1.0.dist-info/entry_points.txt
ddv_printing-0.1.0.dist-info/WHEEL
ddv_printing-0.1.0.dist-info/METADATA
ddv_printing-0.1.0.dist-info/RECORD
