Metadata-Version: 2.1
Name: ddv-printing
Version: 0.1.0
Summary: 
Author: Davide Vitelaru
Author-email: davide@vitelaru.com
Requires-Python: >=3.7,<4.0
Classifier: Programming Language :: Python :: 3
Classifier: Programming Language :: Python :: 3.7
Classifier: Programming Language :: Python :: 3.8
Requires-Dist: colorama (>=0.4.3,<0.5.0)
